_cffi__x14c9b1e1xa60e574a.so
_cffi__x47b53301x507233d5.so
_cffi__x64f2c5c2x6c65de35.so
_cffi__xe6f6e3c8xf914a2ce.so
_cffi__xebcd5da1xb776a8c.so
atomic/__init__.py
atomic/_reference.c
atomic/_reference.so
atomic/reference.py
atomic/__pycache__/_cffi__x14c9b1e1xa60e574a.c
atomic/__pycache__/_cffi__x47b53301x507233d5.c
atomic/__pycache__/_cffi__x64f2c5c2x6c65de35.c
atomic/__pycache__/_cffi__xe6f6e3c8xf914a2ce.c
atomic/__pycache__/_cffi__xebcd5da1xb776a8c.c
atomic/com/lapanthere/atomic/Reference.class
atomic/com/lapanthere/atomic/Reference.java
atomic-0.7.2.dist-info/DESCRIPTION.rst
atomic-0.7.2.dist-info/METADATA
atomic-0.7.2.dist-info/pydist.json
atomic-0.7.2.dist-info/RECORD
atomic-0.7.2.dist-info/top_level.txt
atomic-0.7.2.dist-info/WHEEL
tests/__init__.py
tests/test_atomic.py
