Metadata-Version: 2.0
Name: atomic
Version: 0.7.2
Summary: An atomic class that guarantees atomic updates to its contained value.
Home-page: https://github.com/cyberdelia/atomic
Author: Timothée Peignier
Author-email: timothee.peignier@tryphon.org
License: MIT
Platform: UNKNOWN
Classifier: Intended Audience :: Developers
Classifier: License :: OSI Approved :: MIT License
Classifier: Operating System :: OS Independent
Classifier: Programming Language :: Python
Classifier: Programming Language :: Python :: 3
Classifier: Topic :: Utilities
Requires-Dist: cffi
